Kinesis/__init__.py
S3/__init__.py
aws_logging_handlers/__init__.py
aws_logging_handlers/Kinesis/__init__.py
aws_logging_handlers/S3/__init__.py
aws_logging_handlers/tasks/__init__.py
build/lib/Kinesis/__init__.py
build/lib/S3/__init__.py
build/lib/tasks/__init__.py
build/lib/tests/__init__.py
handlers/__init__.py
handlers/Kinesis/__init__.py
handlers/S3/__init__.py
handlers/tasks/__init__.py
tasks/__init__.py
tests/__init__.py
aws_logging_handlers-2.0.1.dist-info/LICENSE
aws_logging_handlers-2.0.1.dist-info/METADATA
aws_logging_handlers-2.0.1.dist-info/WHEEL
aws_logging_handlers-2.0.1.dist-info/top_level.txt
aws_logging_handlers-2.0.1.dist-info/RECORD
