Metadata-Version: 2.1
Name: aws-logging-handlers
Version: 2.0.1
Summary: Logging aws_logging_handlers to AWS services that support S3 and Kinesis stream logging with multiple threads
Home-page: https://github.com/omrikiei/aws_logging_handlers/
Author: Omri Eival
Author-email: omrieival@gmail.com
License: UNKNOWN
Download-URL: https://github.com/omrikiei/aws_logging_handlers/archive/2.0.1.tar.gz
Keywords: logging,s3,aws,handler,amazon,stream,kinesis,firehose
Platform: UNKNOWN
Classifier: Development Status :: 3 - Alpha
Classifier: Intended Audience :: Developers
Classifier: License :: OSI Approved :: MIT License
Classifier: Programming Language :: Python :: 3
Classifier: Programming Language :: Python :: 3.2
Classifier: Programming Language :: Python :: 3.3
Classifier: Programming Language :: Python :: 3.4
Classifier: Programming Language :: Python :: 3.5
Classifier: Programming Language :: Python :: 3.6
Classifier: Programming Language :: Python :: 3.7
Requires-Dist: boto3
